agentgdb/__init__.py
agentgdb/agentgdb.py
agentgdb/system_prompts/stage1.md
agentgdb/system_prompts/stage3.md
agentgdb/system_prompts/stage5.md
agentgdb-0.1.5.dist-info/licenses/LICENSE
agentgdb-0.1.5.dist-info/METADATA
agentgdb-0.1.5.dist-info/WHEEL
agentgdb-0.1.5.dist-info/top_level.txt
agentgdb-0.1.5.dist-info/RECORD
