Metadata-Version: 2.4
Name: agentgdb
Version: 0.1.5
Summary: Natural language interface for GDB
Author-email: John Ravi <jostache@gmail.com>, Zach Johnston <zachtylerjohnston@gmail.com>
License: MIT License
Project-URL: Homepage, https://github.com/jjravi/AgentGDB
Classifier: Programming Language :: Python :: 3
Classifier: License :: OSI Approved :: MIT License
Classifier: Operating System :: OS Independent
Requires-Python: >=3.8
License-File: LICENSE
Requires-Dist: openai>=1.0.0
Dynamic: license-file
